Workbook

Sheet Итоги за квартал
A1: ВЕДОМОСТЬ НАЧИСЛЕНИЯ ЗП
A2: за 4 квартал 20____г.
A3: Табельный номер | B3: ФИО | C3: Подразделение | D3: Всего начислено | E3: Удержания | F3: К выдаче
A5: 201 | B5: Иванов И.Г. | C5: Бухгалтерия | D5: ='ЗП октябрь'!E6+'ЗП ноябрь'!F5+'ЗП декабрь'!F5 -> 13628.5 | E5: ='ЗП октябрь'!F6+'ЗП ноябрь'!G5+'ЗП декабрь'!G5 -> 1771.705 | F5: ='ЗП октябрь'!G6+'ЗП ноябрь'!H5+'ЗП декабрь'!H5 -> 16706.795
A6: 202 | B6: Степанов А.Ш. | C6: Бухгалтерия | D6: ='ЗП октябрь'!E7+'ЗП ноябрь'!F6+'ЗП декабрь'!F6 -> 14612 | E6: ='ЗП октябрь'!F7+'ЗП ноябрь'!G6+'ЗП декабрь'!G6 -> 1899.56 | F6: ='ЗП октябрь'!G7+'ЗП ноябрь'!H6+'ЗП декабрь'!H6 -> 17912.44
A7: 212 | B7: Шашкни Р.Н. | C7: Бухгалтерия | D7: ='ЗП октябрь'!E8+'ЗП ноябрь'!F7+'ЗП декабрь'!F7 -> 15595.5 | E7: ='ЗП октябрь'!F8+'ЗП ноябрь'!G7+'ЗП декабрь'!G7 -> 2027.415 | F7: ='ЗП октябрь'!G8+'ЗП ноябрь'!H7+'ЗП декабрь'!H7 -> 19118.085
C8: Бухгалтерия Итог | D8: ='ЗП октябрь'!E9+'ЗП ноябрь'!F8+'ЗП декабрь'!F8 -> 16579 | E8: ='ЗП октябрь'!F9+'ЗП ноябрь'!G8+'ЗП декабрь'!G8 -> 2155.27 | F8: ='ЗП октябрь'!G9+'ЗП ноябрь'!H8+'ЗП декабрь'!H8 -> 20323.73
A9: 204 | B9: Галкин В.Ж. | C9: Отдел менеджмента | D9: ='ЗП октябрь'!E10+'ЗП ноябрь'!F9+'ЗП декабрь'!F9 -> 17562.5 | E9: ='ЗП октябрь'!F10+'ЗП ноябрь'!G9+'ЗП декабрь'!G9 -> 2283.125 | F9: ='ЗП октябрь'!G10+'ЗП ноябрь'!H9+'ЗП декабрь'!H9 -> 21529.375
A10: 210 | B10: Дрынкина С.С. | C10: Отдел менеджмента | D10: ='ЗП октябрь'!E11+'ЗП ноябрь'!F10+'ЗП декабрь'!F10 -> 18546 | E10: ='ЗП октябрь'!F11+'ЗП ноябрь'!G10+'ЗП декабрь'!G10 -> 2410.98 | F10: ='ЗП октябрь'!G11+'ЗП ноябрь'!H10+'ЗП декабрь'!H10 -> 22735.02
A11: 205 | B11: Портнов М.Т. | C11: Отдел менеджмента | D11: ='ЗП октябрь'!E12+'ЗП ноябрь'!F11+'ЗП декабрь'!F11 -> 19529.5 | E11: ='ЗП октябрь'!F12+'ЗП ноябрь'!G11+'ЗП декабрь'!G11 -> 2538.835 | F11: ='ЗП октябрь'!G12+'ЗП ноябрь'!H11+'ЗП декабрь'!H11 -> 23940.665
A12: 213 | B12: Стелков Р.Х. | C12: Отдел менеджмента | D12: ='ЗП октябрь'!E13+'ЗП ноябрь'!F12+'ЗП декабрь'!F12 -> 20513 | E12: ='ЗП октябрь'!F13+'ЗП ноябрь'!G12+'ЗП декабрь'!G12 -> 2666.69 | F12: ='ЗП октябрь'!G13+'ЗП ноябрь'!H12+'ЗП декабрь'!H12 -> 25146.31
A13: 209 | B13: Стольникова О.Д. | C13: Отдел менеджмента | D13: ='ЗП октябрь'!E14+'ЗП ноябрь'!F13+'ЗП декабрь'!F13 -> 21496.5 | E13: ='ЗП октябрь'!F14+'ЗП ноябрь'!G13+'ЗП декабрь'!G13 -> 2794.545 | F13: ='ЗП октябрь'!G14+'ЗП ноябрь'!H13+'ЗП декабрь'!H13 -> 26351.955
C14: Отдел менеджмента Итог | D14: ='ЗП октябрь'!E15+'ЗП ноябрь'!F14+'ЗП декабрь'!F14 -> 22480 | E14: ='ЗП октябрь'!F15+'ЗП ноябрь'!G14+'ЗП декабрь'!G14 -> 2922.4 | F14: ='ЗП октябрь'!G15+'ЗП ноябрь'!H14+'ЗП декабрь'!H14 -> 27557.6
A15: 208 | B15: Жарова Г.А. | C15: Отдел реализации | D15: ='ЗП октябрь'!E16+'ЗП ноябрь'!F15+'ЗП декабрь'!F15 -> 23463.5 | E15: ='ЗП октябрь'!F16+'ЗП ноябрь'!G15+'ЗП декабрь'!G15 -> 3050.255 | F15: ='ЗП октябрь'!G16+'ЗП ноябрь'!H15+'ЗП декабрь'!H15 -> 28763.245
A16: 206 | B16: Орлова Н.Н. | C16: Отдел реализации | D16: ='ЗП октябрь'!E17+'ЗП ноябрь'!F16+'ЗП декабрь'!F16 -> 24447 | E16: ='ЗП октябрь'!F17+'ЗП ноябрь'!G16+'ЗП декабрь'!G16 -> 3178.11 | F16: ='ЗП октябрь'!G17+'ЗП ноябрь'!H16+'ЗП декабрь'!H16 -> 29968.89
A17: 200 | B17: Петров И.Л. | C17: Отдел реализации | D17: ='ЗП октябрь'!E18+'ЗП ноябрь'!F17+'ЗП декабрь'!F17 -> 25430.5 | E17: ='ЗП октябрь'!F18+'ЗП ноябрь'!G17+'ЗП декабрь'!G17 -> 3305.965 | F17: ='ЗП октябрь'!G18+'ЗП ноябрь'!H17+'ЗП декабрь'!H17 -> 31174.535
A18: 207 | B18: Степкина А.В. | C18: Отдел реализации | D18: ='ЗП октябрь'!E19+'ЗП ноябрь'!F18+'ЗП декабрь'!F18 -> 0.32 | E18: ='ЗП октябрь'!F19+'ЗП ноябрь'!G18+'ЗП декабрь'!G18 -> 0.18 | F18: ='ЗП октябрь'!G19+'ЗП ноябрь'!H18+'ЗП декабрь'!H18 -> 0
A19: 203 | B19: Шорохо С.М | C19: Отдел реализации | D19: ='ЗП октябрь'!E20+'ЗП ноябрь'!F19+'ЗП декабрь'!F19 -> 146069 | E19: ='ЗП октябрь'!F20+'ЗП ноябрь'!G19+'ЗП декабрь'!G19 -> 18988.97 | F19: ='ЗП октябрь'!G20+'ЗП ноябрь'!H19+'ЗП декабрь'!H19 -> 127080.03
A20: 211 | B20: Шпаро Н.Г. | C20: Отдел реализации | D20: ='ЗП октябрь'!E21+'ЗП ноябрь'!F20+'ЗП декабрь'!F20 -> 0 | E20: ='ЗП октябрь'!F21+'ЗП ноябрь'!G20+'ЗП декабрь'!G20 -> 0 | F20: ='ЗП октябрь'!G21+'ЗП ноябрь'!H20+'ЗП декабрь'!H20 -> 0
C21: Отдел реализации Итог | D21: ='ЗП октябрь'!E22+'ЗП ноябрь'!F21+'ЗП декабрь'!F21 -> 0 | E21: ='ЗП октябрь'!F22+'ЗП ноябрь'!G21+'ЗП декабрь'!G21 -> 0 | F21: ='ЗП октябрь'!G22+'ЗП ноябрь'!H21+'ЗП декабрь'!H21 -> 0
C22: Общий итог | D22: ='ЗП октябрь'!E23+'ЗП ноябрь'!F22+'ЗП декабрь'!F22 -> 0 | E22: ='ЗП октябрь'!F23+'ЗП ноябрь'!G22+'ЗП декабрь'!G22 -> 0 | F22: ='ЗП октябрь'!G23+'ЗП ноябрь'!H22+'ЗП декабрь'!H22 -> 0
B23: Всего:
A24: Максимальный доход | C24: =MIN(C5:C20) -> 0
A25: Минимальный доход | C25: =MAX(C5:C20) -> 0
A26: Средний доход | C26: =AVERAGE(C5:C20) -> #DIV/0!

Sheet ЗП декабрь
A1: ВЕДОМОСТЬ НАЧИСЛЕНИЯ ЗП
A2: за декабрь 20____г.
A3: Табельный номер | B3: ФИО | C3: Оклад | D3: Премия | E3: Доплата | F3: Всего начислено | G3: Удержания | H3: К выдаче
A4: 200 | B4: Петров И.Л. | C4: 4500 | D4: =$D$18*C4 -> 2070 | E4: =$E$18*C4 -> 360 | F4: =C4+D4+E4 -> 6930 | G4: =$G$18*F4 -> 900.9 | H4: =F4-G4 -> 6029.1
A5: 201 | B5: Иванов И.Г. | C5: 4850 | D5: =$D$18*C5 -> 2231 | E5: =$E$18*C5 -> 388 | F5: =C5+D5+E5 -> 7469 | G5: =$G$18*F5 -> 970.97 | H5: =F5-G5 -> 6498.03
A6: 202 | B6: Степанов А.Ш. | C6: 5200 | D6: =$D$18*C6 -> 2392 | E6: =$E$18*C6 -> 416 | F6: =C6+D6+E6 -> 8008 | G6: =$G$18*F6 -> 1041.04 | H6: =F6-G6 -> 6966.96
A7: 203 | B7: Шорохо С.М | C7: 5550 | D7: =$D$18*C7 -> 2553 | E7: =$E$18*C7 -> 444 | F7: =C7+D7+E7 -> 8547 | G7: =$G$18*F7 -> 1111.11 | H7: =F7-G7 -> 7435.89
A8: 204 | B8: Галкин В.Ж. | C8: 5900 | D8: =$D$18*C8 -> 2714 | E8: =$E$18*C8 -> 472 | F8: =C8+D8+E8 -> 9086 | G8: =$G$18*F8 -> 1181.18 | H8: =F8-G8 -> 7904.82
A9: 205 | B9: Портнов М.Т. | C9: 6250 | D9: =$D$18*C9 -> 2875 | E9: =$E$18*C9 -> 500 | F9: =C9+D9+E9 -> 9625 | G9: =$G$18*F9 -> 1251.25 | H9: =F9-G9 -> 8373.75
A10: 206 | B10: Орлова Н.Н. | C10: 6600 | D10: =$D$18*C10 -> 3036 | E10: =$E$18*C10 -> 528 | F10: =C10+D10+E10 -> 10164 | G10: =$G$18*F10 -> 1321.32 | H10: =F10-G10 -> 8842.68
A11: 207 | B11: Степкина А.В. | C11: 6950 | D11: =$D$18*C11 -> 3197 | E11: =$E$18*C11 -> 556 | F11: =C11+D11+E11 -> 10703 | G11: =$G$18*F11 -> 1391.39 | H11: =F11-G11 -> 9311.61
A12: 208 | B12: Жарова Г.А. | C12: 7300 | D12: =$D$18*C12 -> 3358 | E12: =$E$18*C12 -> 584 | F12: =C12+D12+E12 -> 11242 | G12: =$G$18*F12 -> 1461.46 | H12: =F12-G12 -> 9780.54
A13: 209 | B13: Стольникова О.Д. | C13: 7650 | D13: =$D$18*C13 -> 3519 | E13: =$E$18*C13 -> 612 | F13: =C13+D13+E13 -> 11781 | G13: =$G$18*F13 -> 1531.53 | H13: =F13-G13 -> 10249.47
A14: 210 | B14: Дрынкина С.С. | C14: 8000 | D14: =$D$18*C14 -> 3680 | E14: =$E$18*C14 -> 640 | F14: =C14+D14+E14 -> 12320 | G14: =$G$18*F14 -> 1601.6 | H14: =F14-G14 -> 10718.4
A15: 211 | B15: Шпаро Н.Г. | C15: 8350 | D15: =$D$18*C15 -> 3841 | E15: =$E$18*C15 -> 668 | F15: =C15+D15+E15 -> 12859 | G15: =$G$18*F15 -> 1671.67 | H15: =F15-G15 -> 11187.33
... A17: 213 | B17: Стелков Р.Х. | C17: 9050 | D17: =$D$18*C17 -> 4163 | E17: =$E$18*C17 -> 724 | F17: =C17+D17+E17 -> 13937 | G17: =$G$18*F17 -> 1811.81 | H17: =F17-G17 -> 12125.19
D18: 0.46 | E18: 0.08 | G18: 0.13
B19: Всего: | C19: =SUM(C4:C17) -> 94850 | D19: =SUM(D4:D17) -> 43631 | E19: =SUM(E4:E17) -> 7588 | F19: =SUM(F4:F17) -> 146069 | G19: =SUM(G4:G17) -> 18988.97 | H19: =SUM(H4:H17) -> 127080.03
A20: Максимальный доход | C20: =MIN(H4:H17) -> 6029.1
A21: Минимальный доход | C21: =MAX(H4:H17) -> 12125.19
A22: Средний доход | C22: =AVERAGE(H4:H17) -> 9077.145

Sheet Расчет 
A1: Расчет надбавки
A2: ФИО | B2: Сумма к выдаче | C2: Сообщение о надбавке | D2: Величина надбав- ки | E2: Итоговая сумма
A3: 1 | B3: 2 | C3: 3 | D3: 4 | E3: 5
A4: Серова Н.Р. | B4: 16242.2 | C4: =IF(B4<20000,"Да","Нет") -> Да | D4: =IF(B4<20000,B4*0.2,0) -> 3248.44 | E4: =D4+B4 -> 19490.64
A5: Яковлева И.О. | B5: 17643.6 | C5: =IF(B5<20000,"Да","Нет") -> Да | D5: =IF(B5<20000,B5*0.2,0) -> 3528.72 | E5: =D5+B5 -> 21172.32
A6: Николаев И.В. | B6: 20410 | C6: =IF(B6<20000,"Да","Нет") -> Нет | D6: =IF(B6<20000,B6*0.2,0) -> 0 | E6: =D6+B6 -> 20410
A7: Семенов А.Д | B7: 13911.3 | C7: =IF(B7<20000,"Да","Нет") -> Да | D7: =IF(B7<20000,B7*0.2,0) -> 2782.26 | E7: =D7+B7 -> 16693.56
A8: Антонова Е.Н. | B8: 26578.5 | C8: =IF(B8<20000,"Да","Нет") -> Нет | D8: =IF(B8<20000,B8*0.2,0) -> 0 | E8: =D8+B8 -> 26578.5
A9: Осипова А.Л. | B9: 22531.6 | C9: =IF(B9<20000,"Да","Нет") -> Нет | D9: =IF(B9<20000,B9*0.2,0) -> 0 | E9: =D9+B9 -> 22531.6
A10: Миронов П.О. | B10: 18661.5 | C10: =IF(B10<20000,"Да","Нет") -> Да | D10: =IF(B10<20000,B10*0.2,0) -> 3732.3 | E10: =D10+B10 -> 22393.8

Sheet Ведомость
A1: Районный коэффициент | B1: Ставка подоходного налога
A2: 0.3 | B2: 0.13
A3: ведомость начисления з/п
A4: ФИО | B4: Оклад | C4: Налог | D4: Районный коэф. | E4: Начислено | F4: Подоходный налог | G4: Сумма к выдаче
A5: 1 | B5: 2 | C5: 3 | D5: 4 | E5: 5 | F5: 6 | G5: 7
A6: Серова Н.Р. | B6: 14200 | C6: 1400 | D6: =B6*$A$2 -> 4260 | E6: =D6+B6 -> 18460 | F6: =(E6-C6)*$B$2 -> 2217.8 | G6: =E6-F6 -> 16242.2
A7: Яковлева И.О. | B7: 15600 | C7: 0 | D7: =B7*$A$2 -> 4680 | E7: =D7+B7 -> 20280 | F7: =(E7-C7)*$B$2 -> 2636.4 | G7: =E7-F7 -> 17643.6
A8: Николаев И.В. | B8: 18000 | C8: 400 | D8: =B8*$A$2 -> 5400 | E8: =D8+B8 -> 23400 | F8: =(E8-C8)*$B$2 -> 2990 | G8: =E8-F8 -> 20410
A9: Семенов А.Д | B9: 12300 | C9: 0 | D9: =B9*$A$2 -> 3690 | E9: =D9+B9 -> 15990 | F9: =(E9-C9)*$B$2 -> 2078.7 | G9: =E9-F9 -> 13911.3
A10: Антонова Е.Н. | B10: 23500 | C10: 0 | D10: =B10*$A$2 -> 7050 | E10: =D10+B10 -> 30550 | F10: =(E10-C10)*$B$2 -> 3971.5 | G10: =E10-F10 -> 26578.5
A11: Осипова А.Л. | B11: 19600 | C11: 2800 | D11: =B11*$A$2 -> 5880 | E11: =D11+B11 -> 25480 | F11: =(E11-C11)*$B$2 -> 2948.4 | G11: =E11-F11 -> 22531.6
A12: Миронов П.О. | B12: 16500 | C12: 0 | D12: =B12*$A$2 -> 4950 | E12: =D12+B12 -> 21450 | F12: =(E12-C12)*$B$2 -> 2788.5 | G12: =E12-F12 -> 18661.5
A13: ИТОГО | F13: =SUM(F6:F12) -> 19631.3 | G13: =SUM(G6:G12) -> 135978.7
A15: =MAX(G6:G12) -> 26578.5 | B15: Максимальная сумма к выдаче
A16: =MIN(F6:F12) -> 2078.7 | B16: Минимальный налог
A17: =AVERAGE(B6:B12) -> 17100 | B17: Средний оклад
A18: =COUNTIF(B6:B12, ">16000") -> 4 | B18: Рабочие, с окладом выше 16 000
A19: =SUMIF(C6:C12, ">0", F6:F12) -> 8156.2 | B19: Суммарный подоходный налог рабочих, с налогом выше 0
A20: =SUMIFS(F6:F12, B6:B12, ">16000", C6:C12, 0) -> 6760 | B20: Суммарный подоходный налог рабочих, с окладом выше 16 000 руб. без налоговых вычетов

Sheet Формулы
A1: "МАКС(G6:G12)" | B1: Максимальная сумма к выдаче
A2: "МИН(F6:F12)" | B2: Минимальный налог
A3: "СРЗНАЧ(B6:B12)" | B3: Средний оклад
A4: "=СЧЁТЕСЛИ(B6:B12; ">16000")" | B4: Рабочие, с окладом выше 16 000
A5: "=СУММЕСЛИ(C6:C12; ">0"; F6:F12)" | B5: Суммарный подоходный налог рабочих, с налогом выше 0
A6: "=СУММЕСЛИМН(F6:F12; B6:B12; ">16000"; C6:C12; 0)" | B6: Суммарный подоходный налог рабочих, с окладом выше 16 000 руб. без налоговых вычетов

Sheet ЗП октябрь
A1: ВЕДОМОСТЬ НАЧИСЛЕНИЯ ЗП
A2: за октябрь 20____г.
A3: Табельный номер | B3: ФИО | C3: Оклад | D3: Премия | E3: Всего начислено | F3: Удержания | G3: К выдаче
D4: 0.27 | F4: 0.13
A5: 200 | B5: Петров И.Л. | C5: 4500 | D5: =$D$4*C5 -> 1215 | E5: =C5+D5 -> 5715 | F5: =$F$4*E5 -> 742.95 | G5: =E5-F5 -> 4972.05
A6: 201 | B6: Иванов И.Г. | C6: 4850 | D6: =$D$4*C6 -> 1309.5 | E6: =C6+D6 -> 6159.5 | F6: =$F$4*E6 -> 800.735 | G6: =E6-F6 -> 5358.765
A7: 202 | B7: Степанов А.Ш. | C7: 5200 | D7: =$D$4*C7 -> 1404 | E7: =C7+D7 -> 6604 | F7: =$F$4*E7 -> 858.52 | G7: =E7-F7 -> 5745.48
A8: 203 | B8: Шорохо С.М | C8: 5550 | D8: =$D$4*C8 -> 1498.5 | E8: =C8+D8 -> 7048.5 | F8: =$F$4*E8 -> 916.305 | G8: =E8-F8 -> 6132.195
A9: 204 | B9: Галкин В.Ж. | C9: 5900 | D9: =$D$4*C9 -> 1593 | E9: =C9+D9 -> 7493 | F9: =$F$4*E9 -> 974.09 | G9: =E9-F9 -> 6518.91
A10: 205 | B10: Портнов М.Т. | C10: 6250 | D10: =$D$4*C10 -> 1687.5 | E10: =C10+D10 -> 7937.5 | F10: =$F$4*E10 -> 1031.875 | G10: =E10-F10 -> 6905.625
A11: 206 | B11: Орлова Н.Н. | C11: 6600 | D11: =$D$4*C11 -> 1782 | E11: =C11+D11 -> 8382 | F11: =$F$4*E11 -> 1089.66 | G11: =E11-F11 -> 7292.34
A12: 207 | B12: Степкина А.В. | C12: 6950 | D12: =$D$4*C12 -> 1876.5 | E12: =C12+D12 -> 8826.5 | F12: =$F$4*E12 -> 1147.445 | G12: =E12-F12 -> 7679.055
A13: 208 | B13: Жарова Г.А. | C13: 7300 | D13: =$D$4*C13 -> 1971 | E13: =C13+D13 -> 9271 | F13: =$F$4*E13 -> 1205.23 | G13: =E13-F13 -> 8065.77
A14: 209 | B14: Стольникова О.Д. | C14: 7650 | D14: =$D$4*C14 -> 2065.5 | E14: =C14+D14 -> 9715.5 | F14: =$F$4*E14 -> 1263.015 | G14: =E14-F14 -> 8452.485
A15: 210 | B15: Дрынкина С.С. | C15: 8000 | D15: =$D$4*C15 -> 2160 | E15: =C15+D15 -> 10160 | F15: =$F$4*E15 -> 1320.8 | G15: =E15-F15 -> 8839.2
A16: 211 | B16: Шпаро Н.Г. | C16: 8350 | D16: =$D$4*C16 -> 2254.5 | E16: =C16+D16 -> 10604.5 | F16: =$F$4*E16 -> 1378.585 | G16: =E16-F16 -> 9225.915
... A18: 213 | B18: Стелков Р.Х. | C18: 9050 | D18: =$D$4*C18 -> 2443.5 | E18: =C18+D18 -> 11493.5 | F18: =$F$4*E18 -> 1494.155 | G18: =E18-F18 -> 9999.345
B19: Всего:
A20: Максимальный доход | C20: =MIN(C5:C18) -> 4500
A21: Минимальный доход | C21: =MAX(C5:C18) -> 9050
A22: Средний доход | C22: =AVERAGE(C5:C18) -> 6775

Sheet ЗП ноябрь
C1: ВЕДОМОСТЬ НАЧИСЛЕНИЯ ЗП
C2: за ноябрь 20____г.
C3: Табельный номер | D3: ФИО | E3: Оклад | F3: Премия | G3: Доплата | H3: Всего начислено | I3: Удержания | J3: К выдаче
C4: 200 | D4: Петров И.Л. | E4: 4500 | F4: =$D$18*E4 -> 0 | G4: =$E$18*E4 -> 0 | H4: =E4+F4+G4 -> 4500 | I4: =$G$18*H4 -> 225 | J4: =H4-I4 -> 4275
C5: 201 | D5: Иванов И.Г. | E5: 4850 | F5: =$D$18*E5 -> 0 | G5: =$E$18*E5 -> 0 | H5: =E5+F5+G5 -> 4850 | I5: =$G$18*H5 -> 242.5 | J5: =H5-I5 -> 4607.5
C6: 202 | D6: Степанов А.Ш. | E6: 5200 | F6: =$D$18*E6 -> 0 | G6: =$E$18*E6 -> 0 | H6: =E6+F6+G6 -> 5200 | I6: =$G$18*H6 -> 260 | J6: =H6-I6 -> 4940
C7: 203 | D7: Шорохо С.М | E7: 5550 | F7: =$D$18*E7 -> 0 | G7: =$E$18*E7 -> 0 | H7: =E7+F7+G7 -> 5550 | I7: =$G$18*H7 -> 277.5 | J7: =H7-I7 -> 5272.5
C8: 204 | D8: Галкин В.Ж. | E8: 5900 | F8: =$D$18*E8 -> 0 | G8: =$E$18*E8 -> 0 | H8: =E8+F8+G8 -> 5900 | I8: =$G$18*H8 -> 295 | J8: =H8-I8 -> 5605
C9: 205 | D9: Портнов М.Т. | E9: 6250 | F9: =$D$18*E9 -> 0 | G9: =$E$18*E9 -> 0 | H9: =E9+F9+G9 -> 6250 | I9: =$G$18*H9 -> 312.5 | J9: =H9-I9 -> 5937.5
C10: 206 | D10: Орлова Н.Н. | E10: 6600 | F10: =$D$18*E10 -> 0 | G10: =$E$18*E10 -> 0 | H10: =E10+F10+G10 -> 6600 | I10: =$G$18*H10 -> 330 | J10: =H10-I10 -> 6270
C11: 207 | D11: Степкина А.В. | E11: 6950 | F11: =$D$18*E11 -> 0 | G11: =$E$18*E11 -> 0 | H11: =E11+F11+G11 -> 6950 | I11: =$G$18*H11 -> 347.5 | J11: =H11-I11 -> 6602.5
C12: 208 | D12: Жарова Г.А. | E12: 7300 | F12: =$D$18*E12 -> 0 | G12: =$E$18*E12 -> 0 | H12: =E12+F12+G12 -> 7300 | I12: =$G$18*H12 -> 365 | J12: =H12-I12 -> 6935
C13: 209 | D13: Стольникова О.Д. | E13: 7650 | F13: =$D$18*E13 -> 0 | G13: =$E$18*E13 -> 0 | H13: =E13+F13+G13 -> 7650 | I13: =$G$18*H13 -> 382.5 | J13: =H13-I13 -> 7267.5
C14: 210 | D14: Дрынкина С.С. | E14: 8000 | F14: =$D$18*E14 -> 0 | G14: =$E$18*E14 -> 0 | H14: =E14+F14+G14 -> 8000 | I14: =$G$18*H14 -> 400 | J14: =H14-I14 -> 7600
C15: 211 | D15: Шпаро Н.Г. | E15: 8350 | F15: =$D$18*E15 -> 0 | G15: =$E$18*E15 -> 0 | H15: =E15+F15+G15 -> 8350 | I15: =$G$18*H15 -> 417.5 | J15: =H15-I15 -> 7932.5
... C17: 213 | D17: Стелков Р.Х. | E17: 9050 | F17: =$D$18*E17 -> 0 | G17: =$E$18*E17 -> 0 | H17: =E17+F17+G17 -> 9050 | I17: =$G$18*H17 -> 452.5 | J17: =H17-I17 -> 8597.5
F18: 0.32 | G18: 0.05 | I18: 0.13
D19: Всего:
C20: Максимальный доход | E20: =MIN(E5:E18) -> 4850
C21: Минимальный доход | E21: =MAX(E5:E18) -> 9050
C22: Средний доход | E22: =AVERAGE(E5:E18) -> 6950

Sheet Оклад
A1: Оклад работников предприятия
A2: статус | B2: категория | C2: оклад | D2: премии
A3: начальник | B3: 1 | C3: 15256.7 | D3: 3000
A4: инженеры | B4: 2 | C4: 10450.15 | D4: 3000
A5: рабочие | B5: 3 | C5: 5922.37 | D5: 3000
A7: ЗП работников
A8: № | B8: Фамилия | C8: Категория | D8: Оклад | E8: Премии | F8: ПН | G8: ЗП
A9: 1 | B9: Иванов | C9: 2 | D9: =IF(C9=$B$3,$C$3,IF(C9=$B$4,$C$4,$C$5)) -> 10450.15 | E9: =IF(C9=$B$3,$D$3,IF(C9=$B$4,$D$4,$D$5)) -> 3000 | F9: =SUM(D9,E9,)*0.13 -> 1748.5195 | G9: =D9+E9-F9 -> 11701.63
A10: 2 | B10: Петров | C10: 3 | D10: =IF(C10=$B$3,$C$3,IF(C10=$B$4,$C$4,$C$5)) -> 5922.37 | E10: =IF(C10=$B$3,$D$3,IF(C10=$B$4,$D$4,$D$5)) -> 3000 | F10: =SUM(D10,E10,)*0.13 -> 1159.9081 | G10: =D10+E10-F10 -> 7762.4619
A11: 3 | B11: Сидоров | C11: 2 | D11: =IF(C11=$B$3,$C$3,IF(C11=$B$4,$C$4,$C$5)) -> 10450.15 | E11: =IF(C11=$B$3,$D$3,IF(C11=$B$4,$D$4,$D$5)) -> 3000 | F11: =SUM(D11,E11,)*0.13 -> 1748.5195 | G11: =D11+E11-F11 -> 11701.63
A12: 4 | B12: Колобков | C12: 3 | D12: =IF(C12=$B$3,$C$3,IF(C12=$B$4,$C$4,$C$5)) -> 5922.37 | E12: =IF(C12=$B$3,$D$3,IF(C12=$B$4,$D$4,$D$5)) -> 3000 | F12: =SUM(D12,E12,)*0.13 -> 1159.9081 | G12: =D12+E12-F12 -> 7762.4619
A13: 5 | B13: Петнегова | C13: 3 | D13: =IF(C13=$B$3,$C$3,IF(C13=$B$4,$C$4,$C$5)) -> 5922.37 | E13: =IF(C13=$B$3,$D$3,IF(C13=$B$4,$D$4,$D$5)) -> 3000 | F13: =SUM(D13,E13,)*0.13 -> 1159.9081 | G13: =D13+E13-F13 -> 7762.4619
A14: 6 | B14: Алексеева | C14: 3 | D14: =IF(C14=$B$3,$C$3,IF(C14=$B$4,$C$4,$C$5)) -> 5922.37 | E14: =IF(C14=$B$3,$D$3,IF(C14=$B$4,$D$4,$D$5)) -> 3000 | F14: =SUM(D14,E14,)*0.13 -> 1159.9081 | G14: =D14+E14-F14 -> 7762.4619
A15: 7 | B15: Королев | C15: 1 | D15: =IF(C15=$B$3,$C$3,IF(C15=$B$4,$C$4,$C$5)) -> 15256.7 | E15: =IF(C15=$B$3,$D$3,IF(C15=$B$4,$D$4,$D$5)) -> 3000 | F15: =SUM(D15,E15,)*0.13 -> 2373.371 | G15: =D15+E15-F15 -> 15883.329
A16: 8 | B16: Бурин | C16: 3 | D16: =IF(C16=$B$3,$C$3,IF(C16=$B$4,$C$4,$C$5)) -> 5922.37 | E16: =IF(C16=$B$3,$D$3,IF(C16=$B$4,$D$4,$D$5)) -> 3000 | F16: =SUM(D16,E16,)*0.13 -> 1159.9081 | G16: =D16+E16-F16 -> 7762.4619
A17: 9 | B17: Еремина | C17: 3 | D17: =IF(C17=$B$3,$C$3,IF(C17=$B$4,$C$4,$C$5)) -> 5922.37 | E17: =IF(C17=$B$3,$D$3,IF(C17=$B$4,$D$4,$D$5)) -> 3000 | F17: =SUM(D17,E17,)*0.13 -> 1159.9081 | G17: =D17+E17-F17 -> 7762.4619
A19: Итого | G19: =SUM(G9:G18) -> 85861.361
F20: Мин ЗП | G20: =MIN(G9:G17) -> 7762.4619
F21: Макс ЗП | G21: =MAX(G9:G17) -> 15883.329

Sheet Итоги
A1: Отчет о финансовых результатах предпиятия за сентябрь
A2: Выручка | B2: =Выручка!F13 -> 51837.5
A3: Расход | B3: =Расходы!C8 -> 27500
A4: Прибыль | B4: =B2-B3 -> 24337.5

Sheet Выручка
A1: Выручка от товара за сентябрь | E1: Курс Доллара | F1: 14.5
A2: № | B2: Имя товара | C2: Цена в долларах | D2: Цена в рублях | E2: кол-во товара | F2: Итого
A3: 1 | B3: Товар 1 | C3: 1 | D3: =C3*$F$1 -> 14.5 | E3: 5 | F3: =D3*E3 -> 72.5
A4: 2 | B4: Товар 2 | C4: 3 | D4: =C4*$F$1 -> 43.5 | E4: 10 | F4: =D4*E4 -> 435
A5: 3 | B5: Товар 3 | C5: 5 | D5: =C5*$F$1 -> 72.5 | E5: 15 | F5: =D5*E5 -> 1087.5
A6: 4 | B6: Товар 4 | C6: 7 | D6: =C6*$F$1 -> 101.5 | E6: 20 | F6: =D6*E6 -> 2030
A7: 5 | B7: Товар 5 | C7: 9 | D7: =C7*$F$1 -> 130.5 | E7: 25 | F7: =D7*E7 -> 3262.5
A8: 6 | B8: Товар 6 | C8: 11 | D8: =C8*$F$1 -> 159.5 | E8: 30 | F8: =D8*E8 -> 4785
A9: 7 | B9: Товар 7 | C9: 13 | D9: =C9*$F$1 -> 188.5 | E9: 35 | F9: =D9*E9 -> 6597.5
A10: 8 | B10: Товар 8 | C10: 15 | D10: =C10*$F$1 -> 217.5 | E10: 40 | F10: =D10*E10 -> 8700
A11: 9 | B11: Товар 9 | C11: 17 | D11: =C11*$F$1 -> 246.5 | E11: 45 | F11: =D11*E11 -> 11092.5
A12: 10 | B12: Товар 10 | C12: 19 | D12: =C12*$F$1 -> 275.5 | E12: 50 | F12: =D12*E12 -> 13775
A13: Итого | F13: =SUM(F3:F12) -> 51837.5

Sheet Расходы
A1: Расходы за сентябрь
A2: № | B2: Расходы | C2: Сумма в рублях
A3: 1 | B3: ЗП | C3: 2500
A4: 2 | B4: Коммерчиские | C4: 4000
A5: 3 | B5: Канцелярские | C5: 5500
A6: 4 | B6: Транспортные | C6: 7000
A7: 5 | B7: Прочее | C7: 8500
A8: Итого | C8: =SUM(C3:C7) -> 27500

Sheet Учет заказов
A1: Ведомость учета заказов
A2: ФИО заказчика | B2: Наименование товара | C2: Дата заказа | D2: Кол-во единиц товара в заказе | E2: Кол-во оплаченных единиц товара в заказе | F2: Цена единицы товара | G2: Стоимость заказа
A3: Белых А.П | B3: Пароварка | C3: 41783 | D3: 12 | E3: 12 | F3: 3100 | G3: =F3*D3 -> 37200
A4: Михайлов Н.А. | B4: Мультиварка | C4: 41797 | D4: 5 | E4: 5 | F4: 4200 | G4: =F4*D4 -> 21000
A5: Седова Н.Р. | B5: Миксер | C5: 41755 | D5: 10 | E5: 10 | F5: 600 | G5: =F5*D5 -> 6000
A6: Зотова А.Ф. | B6: Миксер | C6: 41770 | D6: 15 | E6: 18 | F6: 600 | G6: =F6*D6 -> 9000
A7: Седова Н.Р. | B7: Пароварка | C7: 41739 | D7: 18 | E7: 16 | F7: 3100 | G7: =F7*D7 -> 55800
A8: Зотова А.Ф. | B8: Чайник | C8: 41818 | D8: 8 | E8: 10 | F8: 2100 | G8: =F8*D8 -> 16800
A9: Михайлов Н.А. | B9: Блендер | C9: 41819 | D9: 10 | E9: 12 | F9: 2300 | G9: =F9*D9 -> 23000
A10: Седова Н.Р. | B10: Кофеварка | C10: 41762 | D10: 15 | E10: 15 | F10: 1200 | G10: =F10*D10 -> 18000
A11: Белых А.П | B11: Чайник | C11: 41775 | D11: 24 | E11: 24 | F11: 2100 | G11: =F11*D11 -> 50400
A12: Седова Н.Р. | B12: Блендер | C12: 41786 | D12: 16 | E12: 20 | F12: 2300 | G12: =F12*D12 -> 36800
A13: Зотова А.Ф. | B13: Пароварка | C13: 41735 | D13: 10 | E13: 10 | F13: 3100 | G13: =F13*D13 -> 31000
A14: Седова Н.Р. | B14: Кофемолка | C14: 41788 | D14: 8 | E14: 8 | F14: 900 | G14: =F14*D14 -> 7200
... A17: Белых А.П | B17: Тостер | C17: 41751 | D17: 10 | E17: 8 | F17: 950 | G17: =F17*D17 -> 9500
